[
  {
    "ContainingType": "GestionProductos.Controllers.ProductosController",
    "Method": "Get",
    "RelativePath": "api/Productos",
    "HttpMethod": "GET",
    "IsController": true,
    "Order": 0,
    "Parameters": [],
    "ReturnTypes": []
  },
  {
    "ContainingType": "GestionProductos.Controllers.ProductosController",
    "Method": "Post",
    "RelativePath": "api/Productos",
    "HttpMethod": "POST",
    "IsController": true,
    "Order": 0,
    "Parameters": [
      {
        "Name": "request",
        "Type": "GestionProductos.Models.Producto",
        "IsRequired": true
      }
    ],
    "ReturnTypes": [
      {
        "Type": "System.Void",
        "MediaTypes": [],
        "StatusCode": 200
      }
    ]
  },
  {
    "ContainingType": "GestionProductos.Controllers.VentasController",
    "Method": "Get",
    "RelativePath": "api/Ventas",
    "HttpMethod": "GET",
    "IsController": true,
    "Order": 0,
    "Parameters": [],
    "ReturnTypes": []
  },
  {
    "ContainingType": "GestionProductos.Controllers.VentasController",
    "Method": "Post",
    "RelativePath": "api/Ventas",
    "HttpMethod": "POST",
    "IsController": true,
    "Order": 0,
    "Parameters": [
      {
        "Name": "request",
        "Type": "GestionProductos.Models.Factura",
        "IsRequired": true
      }
    ],
    "ReturnTypes": [
      {
        "Type": "System.Void",
        "MediaTypes": [],
        "StatusCode": 200
      }
    ]
  },
  {
    "ContainingType": "GestionProductos.Controllers.VentasController",
    "Method": "Put",
    "RelativePath": "api/Ventas/{id}",
    "HttpMethod": "PUT",
    "IsController": true,
    "Order": 0,
    "Parameters": [
      {
        "Name": "idFactura",
        "Type": "System.Int32",
        "IsRequired": false
      },
      {
        "Name": "request",
        "Type": "GestionProductos.Models.Factura",
        "IsRequired": true
      },
      {
        "Name": "id",
        "Type": "",
        "IsRequired": true
      }
    ],
    "ReturnTypes": [
      {
        "Type": "System.Void",
        "MediaTypes": [],
        "StatusCode": 200
      }
    ]
  }
]